musicntd/__init__.py
musicntd/autosimilarity_segmentation.py
musicntd/data_manipulation.py
musicntd/tensor_factory.py
musicntd/model/__init__.py
musicntd/model/current_plot.py
musicntd/model/errors.py
musicntd/model/features.py
musicntd/scripts/__init__.py
musicntd/scripts/default_path.py
musicntd/scripts/final_tests.py
musicntd/scripts/hide_code.py
musicntd/scripts/overall_scripts.py
musicntd-0.3.0.dist-info/AUTHORS
musicntd-0.3.0.dist-info/LICENSE
musicntd-0.3.0.dist-info/METADATA
musicntd-0.3.0.dist-info/WHEEL
musicntd-0.3.0.dist-info/top_level.txt
musicntd-0.3.0.dist-info/RECORD
