Metadata-Version: 2.1
Name: musicntd
Version: 0.3.0
Summary: Package for NTD applied on musical segmentation
Home-page: https://gitlab.inria.fr/amarmore/musicntd
Author: Marmoret Axel
Author-email: axel.marmoret@irisa.fr
License: BSD
Platform: UNKNOWN
Classifier: License :: OSI Approved :: BSD License
Classifier: Programming Language :: Python
Classifier: Development Status :: 3 - Alpha
Classifier: Intended Audience :: Developers
Classifier: Intended Audience :: Science/Research
Classifier: Topic :: Multimedia :: Sound/Audio :: Analysis
Classifier: Programming Language :: Python :: 3.7
Requires-Python: >=3.7
License-File: LICENSE
License-File: AUTHORS
Requires-Dist: librosa (>=0.7.0)
Requires-Dist: madmom
Requires-Dist: matplotlib
Requires-Dist: mir-eval
Requires-Dist: mirdata
Requires-Dist: nn-fac (==0.2.0)
Requires-Dist: numpy (>=1.18.0)
Requires-Dist: pandas
Requires-Dist: scipy (>=0.13.0)
Requires-Dist: soundfile
Requires-Dist: tensorly (>=0.4.5)
